cnhd/__init__.py
cnhd/core/__init__.py
cnhd/core/common.py
cnhd/core/data_helper.py
cnhd/files/data_cn.txt
cnhd/files/data_hk.txt
cnhd/tools/__init__.py
cnhd/tools/cmd.py
cnhd/zpl/__init__.py
cnhd/zpl/exchange_calendar_hkex.py
cnhd/zpl/exchange_calendar_shsz.py
cnhd/zpl/reg.py
cnhd-1.4.dist-info/DESCRIPTION.rst
cnhd-1.4.dist-info/METADATA
cnhd-1.4.dist-info/RECORD
cnhd-1.4.dist-info/WHEEL
cnhd-1.4.dist-info/entry_points.txt
cnhd-1.4.dist-info/metadata.json
cnhd-1.4.dist-info/top_level.txt
tests/__init__.py
tests/data_helper_test.py
